ourpy/__init__.py
ourpy/ourpy.py
ourpy-1.1.3.dist-info/LICENSE
ourpy-1.1.3.dist-info/METADATA
ourpy-1.1.3.dist-info/WHEEL
ourpy-1.1.3.dist-info/top_level.txt
ourpy-1.1.3.dist-info/RECORD
