Metadata-Version: 2.1
Name: ourpy
Version: 1.1.3
Summary: OurPy the beginner friendly Python module
Author: harimtim
License: MIT
Project-URL: GitHub, https://github.com/harimtim/OurPy
Keywords: ourpy,beginner,easy
Classifier: Development Status :: 5 - Production/Stable
Classifier: License :: OSI Approved :: MIT License
Classifier: Intended Audience :: Developers
Classifier: Operating System :: OS Independent
Classifier: Programming Language :: Python :: 3
Requires-Python: >=3
License-File: LICENSE
Requires-Dist: photrack
Requires-Dist: netifaces
Requires-Dist: pythonping
Requires-Dist: colorama
Requires-Dist: art
